krcg_cli/__init__.py
krcg_cli/__main__.py
krcg_cli/parser.py
krcg_cli/subcommands/__init__.py
krcg_cli/subcommands/_utils.py
krcg_cli/subcommands/affinity.py
krcg_cli/subcommands/build.py
krcg_cli/subcommands/card.py
krcg_cli/subcommands/complete.py
krcg_cli/subcommands/deck.py
krcg_cli/subcommands/format.py
krcg_cli/subcommands/search.py
krcg_cli/subcommands/seating.py
krcg_cli/subcommands/stats.py
krcg_cli/subcommands/top.py
krcg_cli/subcommands/twd.py
krcg_cli-2.8.dist-info/LICENSE
krcg_cli-2.8.dist-info/METADATA
krcg_cli-2.8.dist-info/WHEEL
krcg_cli-2.8.dist-info/entry_points.txt
krcg_cli-2.8.dist-info/top_level.txt
krcg_cli-2.8.dist-info/RECORD
