Metadata-Version: 2.1
Name: krcg-cli
Version: 2.8
Summary: KRCG Command Line Interface for VTES
Author-email: Lionel Panhaleux <lionel.panhaleux+krcg@gmail.com>
Project-URL: Repository, https://github.com/lionel-panhaleux/krcg-cli
Keywords: vtes,Vampire: The Eternal Struggle,CCG,TWD,TWDA,CLI
Classifier: Programming Language :: Python :: 3
Classifier: Programming Language :: Python :: 3.11
Classifier: License :: OSI Approved :: MIT License
Classifier: Development Status :: 4 - Beta
Classifier: Intended Audience :: Developers
Classifier: Natural Language :: English
Classifier: Operating System :: OS Independent
Classifier: Environment :: Console
Classifier: Topic :: Games/Entertainment
Requires-Python: >=3.11
License-File: LICENSE
Requires-Dist: aiohttp
Requires-Dist: arrow
Requires-Dist: case-converter
Requires-Dist: requests
Requires-Dist: tqdm
Requires-Dist: unidecode
Requires-Dist: krcg >=3.7
Provides-Extra: dev
Requires-Dist: black ; extra == 'dev'
Requires-Dist: ipython ; extra == 'dev'
Requires-Dist: pytest ; extra == 'dev'
Requires-Dist: ruff ; extra == 'dev'
Requires-Dist: zest.releaser[recommended] ; extra == 'dev'
